med_chat/__init__.py
med_chat/abc.py
med_chat/chatgpt.py
med_chat-0.1.0.dist-info/LICENSE
med_chat-0.1.0.dist-info/METADATA
med_chat-0.1.0.dist-info/WHEEL
med_chat-0.1.0.dist-info/top_level.txt
med_chat-0.1.0.dist-info/RECORD
